InstaWebBot/Instabot.py
InstaWebBot/__init__.py
InstaWebBot/version.py
InstaWebBot-0.3.0.dist-info/LICENSE
InstaWebBot-0.3.0.dist-info/METADATA
InstaWebBot-0.3.0.dist-info/WHEEL
InstaWebBot-0.3.0.dist-info/top_level.txt
InstaWebBot-0.3.0.dist-info/RECORD
