Metadata-Version: 2.1
Name: InstaWebBot
Version: 0.3.0
Summary: A simple library for managing an Instagram bot as a web application.
Home-page: https://github.com/Julius-W/InstaBot
Author: Julius-W
License: GPL-2.0
Keywords: python,Instagram,bot,automation
Classifier: Development Status :: 4 - Beta
Classifier: Intended Audience :: Developers
Classifier: Programming Language :: Python :: 3
Classifier: Programming Language :: Python :: 3.6
Classifier: Programming Language :: Python :: 3.7
Classifier: Programming Language :: Python :: 3.8
Classifier: Programming Language :: Python :: 3.9
Classifier: Programming Language :: Python :: 3.10
Classifier: Operating System :: OS Independent
Classifier: License :: OSI Approved :: GNU General Public License v2 (GPLv2)
Requires-Python: >=3.6
License-File: LICENSE
Requires-Dist: selenium
